kraken/re/__init__.py
kraken/re/address.py
kraken/re/engine.py
kraken/re/exceptions.py
kraken/re/fields.py
kraken/re/py.typed
kraken/re/rules.py
kraken/re/target.py
kraken/re/util/__init__.py
kraken/re/util/frozendict.py
kraken/re/util/repr.py
kraken/re/util/text.py
kraken_re-0.1.0.dist-info/LICENSE
kraken_re-0.1.0.dist-info/WHEEL
kraken_re-0.1.0.dist-info/METADATA
kraken_re-0.1.0.dist-info/RECORD
